compatibility_lib-0.1.10-py3.6-nspkg.pth
compatibility_lib/compatibility_checker.py
compatibility_lib/compatibility_store.py
compatibility_lib/configs.py
compatibility_lib/dependency_highlighter.py
compatibility_lib/dependency_highlighter_stub.py
compatibility_lib/deprecated_dep_finder.py
compatibility_lib/deprecated_dep_finder_stub.py
compatibility_lib/fake_compatibility_store.py
compatibility_lib/get_compatibility_data.py
compatibility_lib/package.py
compatibility_lib/package_crawler_static.py
compatibility_lib/semver_checker.py
compatibility_lib/test_compatibility_checker.py
compatibility_lib/test_compatibility_store.py
compatibility_lib/test_dependency_highlighter.py
compatibility_lib/test_deprecated_dep_finder.py
compatibility_lib/test_fake_compatibility_store.py
compatibility_lib/test_get_compatibility_data.py
compatibility_lib/test_semver_checker.py
compatibility_lib/test_utils.py
compatibility_lib/utils.py
compatibility_lib/testdata/__init__.py
compatibility_lib/testdata/mock_depinfo_data.py
compatibility_lib-0.1.10.dist-info/METADATA
compatibility_lib-0.1.10.dist-info/WHEEL
compatibility_lib-0.1.10.dist-info/namespace_packages.txt
compatibility_lib-0.1.10.dist-info/top_level.txt
compatibility_lib-0.1.10.dist-info/RECORD
