Metadata-Version: 2.1
Name: compatibility-lib
Version: 0.1.10
Summary: A library to get and store the dependency compatibility status data to BigQuery.
Home-page: https://github.com/GoogleCloudPlatform/cloud-opensource-python/tree/master/compatibility_lib
Author: Cloud Python
Author-email: UNKNOWN
License: Apache-2.0
Platform: UNKNOWN
Classifier: Intended Audience :: Developers
Classifier: Development Status :: 3 - Alpha
Classifier: Programming Language :: Python :: 3
Classifier: License :: OSI Approved :: Apache Software License
